Metadata-Version: 1.0
Name: distvic
Version: 1.0
Summary: Gaussian distributions
Home-page: UNKNOWN
Author: Victor Huerta
Author-email: huertavictor@gmail.com
License: UNKNOWN
Platform: UNKNOWN
